[{"first_name":"Sanford","last_name":"Simonis","street":"40165 Ankunding Parkways","city":"Danielview","state":"Minnesota","zip":"09455-0403","phone":"000.295.6722 x173","email":"Ollie_Moen@hotmail.com","acct_date":"2018-01-16T18:58:38.842Z","active":0},{"first_name":"Danial","last_name":"Kiehn","street":"0536 Willms Club","city":"Port Alverafurt","state":"North Dakota","zip":"83190-2044","phone":"1-345-535-3132","email":"Gardner5@yahoo.com","acct_date":"2018-02-08T17:41:34.702Z","active":0},{"first_name":"Delmer","last_name":"Nader","street":"40122 Joanie Island","city":"Torphybury","state":"Hawaii","zip":"10339","phone":"172.739.0585 x7123","email":"Nikolas.Leffler66@hotmail.com","acct_date":"2018-02-24T12:10:22.003Z","active":1},{"first_name":"Camylle","last_name":"Gutmann","street":"8015 Arne Crossroad","city":"Jacobsberg","state":"Hawaii","zip":"13157","phone":"(048) 008-1110","email":"Carolyne5@yahoo.com","acct_date":"2017-12-17T21:31:04.739Z","active":1},{"first_name":"Caitlyn","last_name":"Spencer","street":"36212 Isabell Summit","city":"Lake Alicia","state":"Tennessee","zip":"27670","phone":"231-463-4108","email":"Caleigh64@hotmail.com","acct_date":"2017-06-07T13:39:17.397Z","active":1},{"first_name":"Destiney","last_name":"Schmeler","street":"726 Rebecca Ridges","city":"Dylanfurt","state":"Massachusetts","zip":"02317","phone":"751.668.2645","email":"Maud.Fisher@yahoo.com","acct_date":"2017-07-08T03:21:26.333Z","active":0},{"first_name":"Gage","last_name":"McGlynn","street":"9894 Blick Greens","city":"Lindfort","state":"Pennsylvania","zip":"42476","phone":"(414) 570-4627","email":"Nellie.Little30@gmail.com","acct_date":"2017-09-05T00:23:40.809Z","active":0},{"first_name":"Layla","last_name":"Robel","street":"255 Gilbert Springs","city":"Leoneport","state":"Arkansas","zip":"62103","phone":"(330) 509-1944","email":"Easter_Bartell5@hotmail.com","acct_date":"2017-09-13T20:05:35.579Z","active":0},{"first_name":"Kyle","last_name":"Lynch","street":"34037 Batz Mission","city":"Millsmouth","state":"Florida","zip":"42607-1675","phone":"1-177-240-6308 x27140","email":"Coy63@gmail.com","acct_date":"2017-07-14T14:46:21.289Z","active":0},{"first_name":"Lamar","last_name":"Schuster","street":"247 Abernathy Locks","city":"Lake Quintonbury","state":"Wyoming","zip":"53836","phone":"(331) 967-0524 x7337","email":"Scarlett.Lind@yahoo.com","acct_date":"2017-11-14T06:26:34.867Z","active":1}]